Metadata-Version: 1.0
Name: gauzz-binom
Version: 1.1
Summary: Binomial and Gaussian distributions
Home-page: UNKNOWN
Author: Hakeem Mabby
Author-email: UNKNOWN
License: UNKNOWN
Platform: UNKNOWN
